Metadata-Version: 1.0
Name: topsbm
Version: 0.1
Summary: A scikit-learn extension for Topic Modelling with Hierarchical Stochastic Block Models
Home-page: https://topsbm.readthedocs.io
Author: Martin Gerlach, Eduardo Altmann, Vijay Raghunath, Joel Nothman
Author-email: martin.gerlach@northwestern.edu
License: GPLv3
Platform: UNKNOWN
